few_shot_learning_nlp/__init__.py
few_shot_learning_nlp/loss.py
few_shot_learning_nlp/utils.py
few_shot_learning_nlp/few_shot_ner_image_documents/__init__.py
few_shot_learning_nlp/few_shot_ner_image_documents/classbite.py
few_shot_learning_nlp/few_shot_ner_image_documents/classbite_dataset.py
few_shot_learning_nlp/few_shot_ner_image_documents/container.py
few_shot_learning_nlp/few_shot_ner_image_documents/image_dataset.py
few_shot_learning_nlp/few_shot_ner_image_documents/splitter.py
few_shot_learning_nlp/few_shot_text_classification/__init__.py
few_shot_learning_nlp/few_shot_text_classification/pattern_exploiting.py
few_shot_learning_nlp/few_shot_text_classification/pattern_exploiting_dataset.py
few_shot_learning_nlp/few_shot_text_classification/setfit.py
few_shot_learning_nlp/few_shot_text_classification/setfit_dataset.py
few_shot_learning_nlp-1.0.4.dist-info/LICENSE
few_shot_learning_nlp-1.0.4.dist-info/METADATA
few_shot_learning_nlp-1.0.4.dist-info/WHEEL
few_shot_learning_nlp-1.0.4.dist-info/top_level.txt
few_shot_learning_nlp-1.0.4.dist-info/RECORD
